<?xml version='1.0' encoding='utf-8'?>
<q:quakeml xmlns="http://quakeml.org/xmlns/bed/1.2" xmlns:q="http://quakeml.org/xmlns/quakeml/1.2" xmlns:ns0="http://anss.org/xmlns/catalog/0.1">
  <eventParameters publicID="smi:local/55503c75-0fde-4f0b-a8e4-bcbb3a341c10">
    <event publicID="quakeml:hv.anss.org/Event/HV/73272062" ns0:datasource="hv" ns0:dataid="hv73272062" ns0:eventsource="hv" ns0:eventid="73272062">
      <preferredOriginID>quakeml:hv.anss.org/Origin/HV/76272057</preferredOriginID>
      <preferredMagnitudeID>quakeml:hv.anss.org/Netmag/HV/95456752</preferredMagnitudeID>
      <type>earthquake</type>
      <creationInfo>
        <agencyID>HV</agencyID>
        <creationTime>2022-12-16T17:49:36.000000Z</creationTime>
        <version>0</version>
      </creationInfo>
      <origin publicID="quakeml:hv.anss.org/Origin/HV/76272057" ns0:datasource="hv" ns0:dataid="hv73272062" ns0:eventsource="hv" ns0:eventid="73272062">
        <time>
          <value>2022-12-16T17:46:31.810000Z</value>
        </time>
        <latitude>
          <value>19.2298336029053</value>
        </latitude>
        <longitude>
          <value>-155.401840209961</value>
        </longitude>
        <depth>
          <value>30290.0009155273</value>
          <uncertainty>779.999971</uncertainty>
        </depth>
        <depthType>from location</depthType>
        <timeFixed>false</timeFixed>
        <epicenterFixed>false</epicenterFixed>
        <methodID>smi:hv.anss.org/origin/BINDER</methodID>
        <type>hypocenter</type>
        <evaluationMode>automatic</evaluationMode>
        <evaluationStatus>preliminary</evaluationStatus>
        <creationInfo>
          <agencyID>HV</agencyID>
          <creationTime>2022-12-16T17:49:36.000000Z</creationTime>
        </creationInfo>
        <originUncertainty>
          <preferredDescription>confidence ellipsoid</preferredDescription>
          <horizontalUncertainty>700.0</horizontalUncertainty>
          <confidenceLevel>95.0</confidenceLevel>
          <confidenceEllipsoid>
            <semiMajorAxisLength>1944.0000048</semiMajorAxisLength>
            <semiMinorAxisLength>792.0000312</semiMinorAxisLength>
            <semiIntermediateAxisLength>1703.9999496</semiIntermediateAxisLength>
            <majorAxisPlunge>74.0</majorAxisPlunge>
            <majorAxisAzimuth>33.0</majorAxisAzimuth>
            <majorAxisRotation>316.0</majorAxisRotation>
          </confidenceEllipsoid>
        </originUncertainty>
      </origin>
      <magnitude publicID="quakeml:hv.anss.org/Netmag/HV/95456752">
        <mag>
          <value>2.1099999</value>
          <uncertainty>0.230000004</uncertainty>
        </mag>
        <type>Md</type>
        <originID>quakeml:hv.anss.org/Origin/HV/76272057</originID>
        <methodID>smi:hv.anss.org/magnitude/hypoinverse</methodID>
        <stationCount>9</stationCount>
        <evaluationMode>automatic</evaluationMode>
        <evaluationStatus>preliminary</evaluationStatus>
        <creationInfo>
          <agencyID>HV</agencyID>
          <creationTime>2022-12-16T17:49:36.000000Z</creationTime>
        </creationInfo>
      </magnitude>
    </event>
  </eventParameters>
</q:quakeml>
