<?xml version='1.0' encoding='utf-8'?>
<q:quakeml xmlns="http://quakeml.org/xmlns/bed/1.2" xmlns:q="http://quakeml.org/xmlns/quakeml/1.2" xmlns:ns0="http://anss.org/xmlns/catalog/0.1">
  <eventParameters publicID="smi:local/9c65062d-1e7e-4894-8f41-f6f69ec66eb7">
    <event publicID="quakeml:hv.anss.org/Event/HV/73269792" ns0:datasource="hv" ns0:dataid="hv73269792" ns0:eventsource="hv" ns0:eventid="73269792">
      <preferredOriginID>quakeml:hv.anss.org/Origin/HV/76269787</preferredOriginID>
      <preferredMagnitudeID>quakeml:hv.anss.org/Netmag/HV/95455637</preferredMagnitudeID>
      <type>earthquake</type>
      <creationInfo>
        <agencyID>HV</agencyID>
        <creationTime>2022-12-15T02:00:04.000000Z</creationTime>
        <version>0</version>
      </creationInfo>
      <origin publicID="quakeml:hv.anss.org/Origin/HV/76269787" ns0:datasource="hv" ns0:dataid="hv73269792" ns0:eventsource="hv" ns0:eventid="73269792">
        <time>
          <value>2022-12-15T01:57:12.690000Z</value>
        </time>
        <latitude>
          <value>19.4376659393311</value>
        </latitude>
        <longitude>
          <value>-155.42399597168</value>
        </longitude>
        <depth>
          <value>3609.99989509583</value>
          <uncertainty>3029.99997</uncertainty>
        </depth>
        <depthType>from location</depthType>
        <timeFixed>false</timeFixed>
        <epicenterFixed>false</epicenterFixed>
        <methodID>smi:hv.anss.org/origin/BINDER</methodID>
        <type>hypocenter</type>
        <evaluationMode>automatic</evaluationMode>
        <evaluationStatus>preliminary</evaluationStatus>
        <creationInfo>
          <agencyID>HV</agencyID>
          <creationTime>2022-12-15T02:00:04.000000Z</creationTime>
        </creationInfo>
        <originUncertainty>
          <preferredDescription>confidence ellipsoid</preferredDescription>
          <horizontalUncertainty>990.0</horizontalUncertainty>
          <confidenceLevel>95.0</confidenceLevel>
          <confidenceEllipsoid>
            <semiMajorAxisLength>7295.999904</semiMajorAxisLength>
            <semiMinorAxisLength>1320.0000288</semiMinorAxisLength>
            <semiIntermediateAxisLength>2376.000024</semiIntermediateAxisLength>
            <majorAxisPlunge>85.0</majorAxisPlunge>
            <majorAxisAzimuth>136.0</majorAxisAzimuth>
            <majorAxisRotation>291.0</majorAxisRotation>
          </confidenceEllipsoid>
        </originUncertainty>
      </origin>
      <magnitude publicID="quakeml:hv.anss.org/Netmag/HV/95455637">
        <mag>
          <value>0.209999993</value>
          <uncertainty>0.200000003</uncertainty>
        </mag>
        <type>Md</type>
        <originID>quakeml:hv.anss.org/Origin/HV/76269787</originID>
        <methodID>smi:hv.anss.org/magnitude/hypoinverse</methodID>
        <stationCount>2</stationCount>
        <evaluationMode>automatic</evaluationMode>
        <evaluationStatus>preliminary</evaluationStatus>
        <creationInfo>
          <agencyID>HV</agencyID>
          <creationTime>2022-12-15T02:00:04.000000Z</creationTime>
        </creationInfo>
      </magnitude>
    </event>
  </eventParameters>
</q:quakeml>
