<?xml version='1.0' encoding='utf-8'?>
<q:quakeml xmlns="http://quakeml.org/xmlns/bed/1.2" xmlns:q="http://quakeml.org/xmlns/quakeml/1.2" xmlns:ns0="http://anss.org/xmlns/catalog/0.1">
  <eventParameters publicID="smi:local/a9f27da4-4ee8-46ca-ae6a-f625c00e3f0b">
    <event publicID="quakeml:hv.anss.org/Event/HV/73251317" ns0:datasource="hv" ns0:dataid="hv73251317" ns0:eventsource="hv" ns0:eventid="73251317">
      <preferredOriginID>quakeml:hv.anss.org/Origin/HV/76251312</preferredOriginID>
      <preferredMagnitudeID>quakeml:hv.anss.org/Netmag/HV/95449722</preferredMagnitudeID>
      <type>earthquake</type>
      <creationInfo>
        <agencyID>HV</agencyID>
        <creationTime>2022-12-02T05:42:08.000000Z</creationTime>
        <version>0</version>
      </creationInfo>
      <origin publicID="quakeml:hv.anss.org/Origin/HV/76251312" ns0:datasource="hv" ns0:dataid="hv73251317" ns0:eventsource="hv" ns0:eventid="73251317">
        <time>
          <value>2022-12-02T05:39:16.210000Z</value>
        </time>
        <latitude>
          <value>19.4155006408691</value>
        </latitude>
        <longitude>
          <value>-155.275161743164</value>
        </longitude>
        <depth>
          <value>10439.9995803833</value>
          <uncertainty>680.000007</uncertainty>
        </depth>
        <depthType>from location</depthType>
        <timeFixed>false</timeFixed>
        <epicenterFixed>false</epicenterFixed>
        <methodID>smi:hv.anss.org/origin/BINDER</methodID>
        <type>hypocenter</type>
        <evaluationMode>automatic</evaluationMode>
        <evaluationStatus>preliminary</evaluationStatus>
        <creationInfo>
          <agencyID>HV</agencyID>
          <creationTime>2022-12-02T05:42:08.000000Z</creationTime>
        </creationInfo>
        <originUncertainty>
          <preferredDescription>confidence ellipsoid</preferredDescription>
          <horizontalUncertainty>570.0</horizontalUncertainty>
          <confidenceLevel>95.0</confidenceLevel>
          <confidenceEllipsoid>
            <semiMajorAxisLength>1776.000024</semiMajorAxisLength>
            <semiMinorAxisLength>767.9999832</semiMinorAxisLength>
            <semiIntermediateAxisLength>1488.000012</semiIntermediateAxisLength>
            <majorAxisPlunge>66.0</majorAxisPlunge>
            <majorAxisAzimuth>350.0</majorAxisAzimuth>
            <majorAxisRotation>5.0</majorAxisRotation>
          </confidenceEllipsoid>
        </originUncertainty>
      </origin>
      <magnitude publicID="quakeml:hv.anss.org/Netmag/HV/95449722">
        <mag>
          <value>0.769999981</value>
          <uncertainty>0.75999999</uncertainty>
        </mag>
        <type>Md</type>
        <originID>quakeml:hv.anss.org/Origin/HV/76251312</originID>
        <methodID>smi:hv.anss.org/magnitude/hypoinverse</methodID>
        <stationCount>2</stationCount>
        <evaluationMode>automatic</evaluationMode>
        <evaluationStatus>preliminary</evaluationStatus>
        <creationInfo>
          <agencyID>HV</agencyID>
          <creationTime>2022-12-02T05:42:08.000000Z</creationTime>
        </creationInfo>
      </magnitude>
    </event>
  </eventParameters>
</q:quakeml>
