<?xml version='1.0' encoding='utf-8'?>
<q:quakeml xmlns="http://quakeml.org/xmlns/bed/1.2" xmlns:q="http://quakeml.org/xmlns/quakeml/1.2" xmlns:ns0="http://anss.org/xmlns/catalog/0.1">
  <eventParameters publicID="smi:local/acdd4cfb-893e-4b4d-899c-7500bbc8e7bf">
    <event publicID="quakeml:hv.anss.org/Event/HV/73270207" ns0:datasource="hv" ns0:dataid="hv73270207" ns0:eventsource="hv" ns0:eventid="73270207">
      <preferredOriginID>quakeml:hv.anss.org/Origin/HV/75090758</preferredOriginID>
      <preferredMagnitudeID>quakeml:hv.anss.org/Netmag/HV/95163898</preferredMagnitudeID>
      <type>earthquake</type>
      <creationInfo>
        <agencyID>HV</agencyID>
        <creationTime>2022-12-15T11:25:08.000000Z</creationTime>
        <version>2</version>
      </creationInfo>
      <origin publicID="quakeml:hv.anss.org/Origin/HV/75090758" ns0:datasource="hv" ns0:dataid="hv73270207" ns0:eventsource="hv" ns0:eventid="73270207">
        <time>
          <value>2022-12-15T10:49:12.200000Z</value>
        </time>
        <latitude>
          <value>19.188</value>
        </latitude>
        <longitude>
          <value>-155.4575</value>
        </longitude>
        <depth>
          <value>34800.0</value>
          <uncertainty>950.0</uncertainty>
        </depth>
        <depthType>from location</depthType>
        <timeFixed>false</timeFixed>
        <epicenterFixed>false</epicenterFixed>
        <methodID>smi:hv.anss.org/origin/HYP2000</methodID>
        <type>hypocenter</type>
        <evaluationMode>manual</evaluationMode>
        <evaluationStatus>final</evaluationStatus>
        <creationInfo>
          <agencyID>HV</agencyID>
          <creationTime>2022-12-15T11:14:49.000000Z</creationTime>
        </creationInfo>
        <originUncertainty>
          <preferredDescription>confidence ellipsoid</preferredDescription>
          <horizontalUncertainty>620.0</horizontalUncertainty>
          <confidenceLevel>95.0</confidenceLevel>
          <confidenceEllipsoid>
            <semiMajorAxisLength>2448.0</semiMajorAxisLength>
            <semiMinorAxisLength>1008.0</semiMinorAxisLength>
            <semiIntermediateAxisLength>1584.0</semiIntermediateAxisLength>
            <majorAxisPlunge>69.0</majorAxisPlunge>
            <majorAxisAzimuth>6.0</majorAxisAzimuth>
            <majorAxisRotation>0.0</majorAxisRotation>
          </confidenceEllipsoid>
        </originUncertainty>
      </origin>
      <magnitude publicID="quakeml:hv.anss.org/Netmag/HV/95163898">
        <mag>
          <value>1.61</value>
          <uncertainty>0.0806428204451641</uncertainty>
        </mag>
        <type>Md</type>
        <originID>quakeml:hv.anss.org/Origin/HV/75090758</originID>
        <methodID>smi:hv.anss.org/magnitude/HypoinvMd</methodID>
        <stationCount>11</stationCount>
        <azimuthalGap>208.605783619262</azimuthalGap>
        <evaluationMode>manual</evaluationMode>
        <evaluationStatus>reviewed</evaluationStatus>
        <creationInfo>
          <agencyID>HV</agencyID>
          <creationTime>2022-12-15T11:25:08.000000Z</creationTime>
        </creationInfo>
      </magnitude>
    </event>
  </eventParameters>
</q:quakeml>
