<?xml version='1.0' encoding='utf-8'?>
<q:quakeml xmlns="http://quakeml.org/xmlns/bed/1.2" xmlns:q="http://quakeml.org/xmlns/quakeml/1.2" xmlns:ns0="http://anss.org/xmlns/catalog/0.1">
  <eventParameters publicID="smi:local/d3814e05-4b8c-45cc-80d8-2eb886e1306d">
    <event publicID="quakeml:hv.anss.org/Event/HV/73288852" ns0:datasource="hv" ns0:dataid="hv73288852" ns0:eventsource="hv" ns0:eventid="73288852">
      <preferredOriginID>quakeml:hv.anss.org/Origin/HV/75091158</preferredOriginID>
      <preferredMagnitudeID>quakeml:hv.anss.org/Netmag/HV/95164548</preferredMagnitudeID>
      <type>earthquake</type>
      <creationInfo>
        <agencyID>HV</agencyID>
        <creationTime>2022-12-31T09:10:39.000000Z</creationTime>
        <version>2</version>
      </creationInfo>
      <origin publicID="quakeml:hv.anss.org/Origin/HV/75091158" ns0:datasource="hv" ns0:dataid="hv73288852" ns0:eventsource="hv" ns0:eventid="73288852">
        <time>
          <value>2022-12-31T08:45:21.600000Z</value>
        </time>
        <latitude>
          <value>19.403</value>
        </latitude>
        <longitude>
          <value>-155.2875</value>
        </longitude>
        <depth>
          <value>870.0</value>
          <uncertainty>350.0</uncertainty>
        </depth>
        <depthType>from location</depthType>
        <timeFixed>false</timeFixed>
        <epicenterFixed>false</epicenterFixed>
        <methodID>smi:hv.anss.org/origin/HYP2000</methodID>
        <type>hypocenter</type>
        <evaluationMode>manual</evaluationMode>
        <evaluationStatus>final</evaluationStatus>
        <creationInfo>
          <agencyID>HV</agencyID>
          <creationTime>2022-12-31T09:08:49.000000Z</creationTime>
        </creationInfo>
        <originUncertainty>
          <preferredDescription>confidence ellipsoid</preferredDescription>
          <horizontalUncertainty>200.0</horizontalUncertainty>
          <confidenceLevel>95.0</confidenceLevel>
          <confidenceEllipsoid>
            <semiMajorAxisLength>936.0</semiMajorAxisLength>
            <semiMinorAxisLength>432.0</semiMinorAxisLength>
            <semiIntermediateAxisLength>480.0</semiIntermediateAxisLength>
            <majorAxisPlunge>65.0</majorAxisPlunge>
            <majorAxisAzimuth>263.0</majorAxisAzimuth>
            <majorAxisRotation>81.0</majorAxisRotation>
          </confidenceEllipsoid>
        </originUncertainty>
      </origin>
      <magnitude publicID="quakeml:hv.anss.org/Netmag/HV/95164548">
        <mag>
          <value>0.22</value>
          <uncertainty>0.0266522279231508</uncertainty>
        </mag>
        <type>Md</type>
        <originID>quakeml:hv.anss.org/Origin/HV/75091158</originID>
        <methodID>smi:hv.anss.org/magnitude/HypoinvMd</methodID>
        <stationCount>2</stationCount>
        <azimuthalGap>252.591300744244</azimuthalGap>
        <evaluationMode>manual</evaluationMode>
        <evaluationStatus>reviewed</evaluationStatus>
        <creationInfo>
          <agencyID>HV</agencyID>
          <creationTime>2022-12-31T09:10:39.000000Z</creationTime>
        </creationInfo>
      </magnitude>
    </event>
  </eventParameters>
</q:quakeml>
