<?xml version='1.0' encoding='utf-8'?>
<q:quakeml xmlns="http://quakeml.org/xmlns/bed/1.2" xmlns:q="http://quakeml.org/xmlns/quakeml/1.2" xmlns:ns0="http://anss.org/xmlns/catalog/0.1">
  <eventParameters publicID="smi:local/79418ac7-6397-4086-b8b9-aadb4a1b7118">
    <event publicID="quakeml:hv.anss.org/Event/HV/73282607" ns0:datasource="hv" ns0:dataid="hv73282607" ns0:eventsource="hv" ns0:eventid="73282607">
      <preferredOriginID>quakeml:hv.anss.org/Origin/HV/76282602</preferredOriginID>
      <preferredMagnitudeID>quakeml:hv.anss.org/Netmag/HV/95461992</preferredMagnitudeID>
      <type>earthquake</type>
      <creationInfo>
        <agencyID>HV</agencyID>
        <creationTime>2022-12-25T17:41:30.000000Z</creationTime>
        <version>0</version>
      </creationInfo>
      <origin publicID="quakeml:hv.anss.org/Origin/HV/76282602" ns0:datasource="hv" ns0:dataid="hv73282607" ns0:eventsource="hv" ns0:eventid="73282607">
        <time>
          <value>2022-12-25T17:38:24.800000Z</value>
        </time>
        <latitude>
          <value>19.4424991607666</value>
        </latitude>
        <longitude>
          <value>-155.398834228516</value>
        </longitude>
        <depth>
          <value>9520.00045776367</value>
          <uncertainty>2539.99996</uncertainty>
        </depth>
        <depthType>from location</depthType>
        <timeFixed>false</timeFixed>
        <epicenterFixed>false</epicenterFixed>
        <methodID>smi:hv.anss.org/origin/BINDER</methodID>
        <type>hypocenter</type>
        <evaluationMode>automatic</evaluationMode>
        <evaluationStatus>preliminary</evaluationStatus>
        <creationInfo>
          <agencyID>HV</agencyID>
          <creationTime>2022-12-25T17:41:30.000000Z</creationTime>
        </creationInfo>
        <originUncertainty>
          <preferredDescription>confidence ellipsoid</preferredDescription>
          <horizontalUncertainty>3340.0</horizontalUncertainty>
          <confidenceLevel>95.0</confidenceLevel>
          <confidenceEllipsoid>
            <semiMajorAxisLength>8736.00024</semiMajorAxisLength>
            <semiMinorAxisLength>3407.999904</semiMinorAxisLength>
            <semiIntermediateAxisLength>6767.999832</semiIntermediateAxisLength>
            <majorAxisPlunge>23.0</majorAxisPlunge>
            <majorAxisAzimuth>31.0</majorAxisAzimuth>
            <majorAxisRotation>349.0</majorAxisRotation>
          </confidenceEllipsoid>
        </originUncertainty>
      </origin>
      <magnitude publicID="quakeml:hv.anss.org/Netmag/HV/95461992">
        <mag>
          <value>0.709999979</value>
          <uncertainty>0.699999988</uncertainty>
        </mag>
        <type>Md</type>
        <originID>quakeml:hv.anss.org/Origin/HV/76282602</originID>
        <methodID>smi:hv.anss.org/magnitude/hypoinverse</methodID>
        <stationCount>2</stationCount>
        <evaluationMode>automatic</evaluationMode>
        <evaluationStatus>preliminary</evaluationStatus>
        <creationInfo>
          <agencyID>HV</agencyID>
          <creationTime>2022-12-25T17:41:30.000000Z</creationTime>
        </creationInfo>
      </magnitude>
    </event>
  </eventParameters>
</q:quakeml>
